xxc/__init__.py
xxc/error.py
xxc/proc.py
xxc-4.0.dist-info/LICENSE
xxc-4.0.dist-info/METADATA
xxc-4.0.dist-info/WHEEL
xxc-4.0.dist-info/top_level.txt
xxc-4.0.dist-info/RECORD
