Metadata-Version: 2.1
Name: xxc
Version: 4.0
Summary: Tools for automating command execution
Home-page: https://github.com/synestematic/xxc
Author: Federico Rizzo
Author-email: synestem@ticATgmail.com
License: MIT
Platform: UNKNOWN
Classifier: Programming Language :: Python :: 3 :: Only
Classifier: Development Status :: 5 - Production/Stable
Classifier: License :: OSI Approved :: MIT License
Classifier: Operating System :: POSIX :: Linux
Classifier: Operating System :: MacOS :: MacOS X
Classifier: Topic :: Software Development :: Libraries :: Python Modules
Classifier: Topic :: Utilities
